pycf_loader/__init__.py
pycf_loader/pycf_loader.cp35-win_amd64.pyd
pycf_loader/pycf_loader.cp36-win_amd64.pyd
pycf_loader/pycf_loader.cp37-win_amd64.pyd
pycf_loader/pycf_loader.cp38-win_amd64.pyd
pycf_loader/pycf_loader.cpython-35m-x86_64-linux-gnu.so
pycf_loader/pycf_loader.cpython-36m-x86_64-linux-gnu.so
pycf_loader/pycf_loader.cpython-37m-x86_64-linux-gnu.so
pycf_loader/pycf_loader.cpython-38-x86_64-linux-gnu.so
pycf_loader-1.1.dist-info/LICENSE.txt
pycf_loader-1.1.dist-info/METADATA
pycf_loader-1.1.dist-info/WHEEL
pycf_loader-1.1.dist-info/top_level.txt
pycf_loader-1.1.dist-info/RECORD
